Metadata-Version: 2.1
Name: task-estimator
Version: 0.9.2
Summary: A supervised learning tool for estimating task duration.
Home-page: https://github.com/chrisspen/estimator
Author: Chris Spencer
Author-email: chrisspen@gmail.com
License: BSD
Platform: UNKNOWN
Classifier: Development Status :: 4 - Beta
Classifier: Intended Audience :: Developers
Classifier: License :: OSI Approved :: BSD License
Classifier: Operating System :: OS Independent
Classifier: Programming Language :: Python
Classifier: Programming Language :: Python :: 3.7
